uv_publish_github/__init__.py
uv_publish_github-0.1.0.dist-info/WHEEL
uv_publish_github-0.1.0.dist-info/entry_points.txt
uv_publish_github-0.1.0.dist-info/METADATA
uv_publish_github-0.1.0.dist-info/RECORD
