Metadata-Version: 2.3
Name: uv-publish-github
Version: 0.1.0
Summary: Add your description here
Author: danielsyahputra
Author-email: danielsyahputra <daniel.purba@dana.id>
Requires-Dist: requests>=2.32.5
Requires-Python: >=3.11
